esmc_function_classifier/__init__.py
esmc_function_classifier/model.py
esmc_function_classifier-0.0.7.dist-info/METADATA
esmc_function_classifier-0.0.7.dist-info/WHEEL
esmc_function_classifier-0.0.7.dist-info/top_level.txt
esmc_function_classifier-0.0.7.dist-info/RECORD
