Metadata-Version: 2.4
Name: esmc-function-classifier
Version: 0.0.7
Summary: An Evolutionary-scale Model (ESM) for protein function prediction from amino acid sequences using the Gene Ontology (GO).
Author: Andrew DalPino
License: MIT
Project-URL: Homepage, https://github.com/andrewdalpino/esmc-function-classifier
Project-URL: Documentation, https://github.com/andrewdalpino/esmc-function-classifier/README.md
Project-URL: Source, https://github.com/andrewdalpino/esmc-function-classifier
Requires-Python: >=3.10
Requires-Dist: esm<4.0.0,>=3.2.0
Requires-Dist: torch<3.0.0,>=2.7.1
Requires-Dist: torchao<0.13.0,>=0.12.0
Requires-Dist: huggingface_hub<0.34.0,>=0.33.4
Requires-Dist: networkx<4.0.0,>=3.4.2
Provides-Extra: dev
Requires-Dist: mypy; extra == "dev"
Requires-Dist: black; extra == "dev"
Requires-Dist: matplotlib; extra == "dev"
Provides-Extra: test
Requires-Dist: mypy; extra == "test"
Requires-Dist: black; extra == "test"
